directionality_quantification/__init__.py
directionality_quantification/main-backup.py
directionality_quantification/main.py
directionality_quantification/plot.py
directionality_quantification/plot_utils.py
directionality_quantification/process.py
directionality_quantification-0.3.0.dist-info/METADATA
directionality_quantification-0.3.0.dist-info/WHEEL
directionality_quantification-0.3.0.dist-info/entry_points.txt
directionality_quantification-0.3.0.dist-info/top_level.txt
directionality_quantification-0.3.0.dist-info/RECORD
