Metadata-Version: 2.4
Name: directionality-quantification
Version: 0.3.0
Summary: Package for cell directionality quantification.
Requires-Python: >=3.11
Requires-Dist: numpy==2.1.3
Requires-Dist: tifffile==2024.9.20
Requires-Dist: pandas==2.2.3
Requires-Dist: matplotlib-scalebar==0.8.1
Requires-Dist: scikit-image==0.24.0
Requires-Dist: openpyxl==3.1.5
Requires-Dist: xlsxwriter==3.2.0
Requires-Dist: xlrd==2.0.1
Requires-Dist: tqdm>=4.67.1
